{
    "collector_id": "683948513",
    "sponsor_id":"711416967",
    "items": [
        {
            "title": "TANQUEO 1,169 gal CORRIENTE",
            "currency_id": "COP",
            "description": "TANQUEO 1,169 gal CORRIENTE",
            "quantity": 1,
            "unit_price": 10000
        }
    ],
    "taxes": [
        {
            "type": "IVA",
            "value": 0
        }
    ],
    "external_reference": "PruebaError",
    "notification_url": "http://mina1.iapropiada.com/payments/mercadopago/notification/1174/PruebaError"
}
